demo/lib/__init__.py
demo/lib/testbed.py
demo/lib/testcase.py
demo/testcases/__init__.py
demo/testcases/tc_sftp.py
demo/testcases/tc_ssh.py
tests/__init__.py
tests/run.py
tests/test_sftp.py
tests/test_ssh.py
tests/test_utils.py
venv/bin/jp.py
venv/bin/rst2html.py
venv/bin/rst2html4.py
venv/bin/rst2html5.py
venv/bin/rst2latex.py
venv/bin/rst2man.py
venv/bin/rst2odt.py
venv/bin/rst2odt_prepstyles.py
venv/bin/rst2pseudoxml.py
venv/bin/rst2s5.py
venv/bin/rst2xetex.py
venv/bin/rst2xml.py
venv/bin/rstpep2html.py
xbot/plugins/ssh/__init__.py
xbot/plugins/ssh/errors.py
xbot/plugins/ssh/sftp.py
xbot/plugins/ssh/ssh.py
xbot/plugins/ssh/utils.py
xbot/plugins/ssh/version.py
xbot.plugins.ssh-0.1.0.dist-info/LICENSE
xbot.plugins.ssh-0.1.0.dist-info/METADATA
xbot.plugins.ssh-0.1.0.dist-info/WHEEL
xbot.plugins.ssh-0.1.0.dist-info/top_level.txt
xbot.plugins.ssh-0.1.0.dist-info/RECORD
