Metadata-Version: 2.1
Name: xbot.plugins.ssh
Version: 0.1.0
Summary: SSH library for xbot.framework
Home-page: https://github.com/zhaowcheng/xbot.plugins.ssh
Author: zhaowcheng
Author-email: zhaowcheng@163.com
License: UNKNOWN
Project-URL: Homepage, https://github.com/zhaowcheng/xbot.plugins.ssh
Project-URL: Issues, https://github.com/zhaowcheng/xbot.plugins.ssh/issues
Platform: UNKNOWN
Classifier: License :: OSI Approved :: BSD License
Classifier: Operating System :: OS Independent
Classifier: Programming Language :: Python :: 3
Classifier: Programming Language :: Python :: 3.6
Classifier: Programming Language :: Python :: 3.7
Classifier: Programming Language :: Python :: 3.8
Classifier: Programming Language :: Python :: 3.9
Classifier: Programming Language :: Python :: 3.10
Classifier: Programming Language :: Python :: 3.11
Classifier: Programming Language :: Python :: 3.12
Requires-Python: >=3.6
License-File: LICENSE
Requires-Dist: xbot.framework (>=0.4.0) ; python_version >= "3.6"
Requires-Dist: paramiko ; python_version >= "3.6"
